.gitignore
LICENSE
MANIFEST.in
README.md
setup.py
Arugula.egg-info/PKG-INFO
Arugula.egg-info/SOURCES.txt
Arugula.egg-info/dependency_links.txt
Arugula.egg-info/entry_points.txt
Arugula.egg-info/top_level.txt
arugula/__init__.py
arugula/main.py
docs/developing.md
docs/releasing.md