Metadata-Version: 1.1
Name: Arugula
Version: 0.0.1-alpha
Summary: a sample Python 3 project for a command-line script
Home-page: https://github.com/cjerdonek/arugula
Author: Chris Jerdonek
Author-email: chris.jerdonek@gmail.com
License: MIT
Keywords: sample python3 project
Platform: UNKNOWN
Classifier: Development Status :: 3 - Alpha
Classifier: Intended Audience :: Developers
Classifier: Topic :: Software Development :: Build Tools
Classifier: License :: OSI Approved :: MIT License
Classifier: Programming Language :: Python :: 3
Classifier: Programming Language :: Python :: 3.4
